spheral/__init__.py
spheral/config.py
spheral/data_models.py
spheral/logger.py
spheral/sphere_models.py
spheral/sphere_utils.py
spheral-0.1.0.dist-info/LICENSE
spheral-0.1.0.dist-info/METADATA
spheral-0.1.0.dist-info/WHEEL
spheral-0.1.0.dist-info/RECORD
