Metadata-Version: 2.3
Name: spheral
Version: 0.1.0
Summary: Spherical representation of data
License: MIT
Author: MauricioSalazare
Requires-Python: >=3.11
Classifier: License :: OSI Approved :: MIT License
Classifier: Programming Language :: Python :: 3
Classifier: Programming Language :: Python :: 3.11
Classifier: Programming Language :: Python :: 3.12
Classifier: Programming Language :: Python :: 3.13
Requires-Dist: numpy (>=2.2.3,<3.0.0)
Requires-Dist: pandas (>=2.2.3,<3.0.0)
Requires-Dist: scipy (>=1.15.2,<2.0.0)
